episimmer/__init__.py
episimmer/agent.py
episimmer/location.py
episimmer/main.py
episimmer/model.py
episimmer/read_file.py
episimmer/simulate.py
episimmer/world.py
episimmer/policy/__init__.py
episimmer/policy/base.py
episimmer/policy/contact_tracing_policy.py
episimmer/policy/lockdown_policy.py
episimmer/policy/testing_policy.py
episimmer/policy/vaccination_policy.py
episimmer/utils/__init__.py
episimmer/utils/arg_parser.py
episimmer/utils/math.py
episimmer/utils/module_handling.py
episimmer/utils/statistics.py
episimmer/utils/time.py
episimmer/utils/visualize.py
episimmer/vulnerability_detection/__init__.py
episimmer/vulnerability_detection/agent_vd.py
episimmer/vulnerability_detection/base.py
episimmer/vulnerability_detection/event_vd.py
episimmer/vulnerability_detection/vd.py
episimmer-2.2.2.dist-info/LICENSE
episimmer-2.2.2.dist-info/METADATA
episimmer-2.2.2.dist-info/WHEEL
episimmer-2.2.2.dist-info/entry_points.txt
episimmer-2.2.2.dist-info/top_level.txt
episimmer-2.2.2.dist-info/RECORD
