Metadata-Version: 2.1
Name: episimmer
Version: 2.2.2
Summary: Epidemic Simulation Platform
Home-page: https://github.com/healthbadge/episimmer
Author: Inavamsi Enaganti, Surya Dheeshjith
Author-email: inavamsi@healthbadge.org, surya@healthbadge.org
License: BSD-3-Clause
Platform: UNKNOWN
Classifier: Programming Language :: Python
Classifier: Programming Language :: Python :: 3.7
Classifier: Programming Language :: Python :: 3.8
Classifier: Development Status :: 5 - Production/Stable
Classifier: Intended Audience :: Science/Research
Classifier: License :: OSI Approved :: BSD License
Classifier: Topic :: Scientific/Engineering
Requires-Python: >=3.7
Requires-Dist: matplotlib (==3.4.2)
Requires-Dist: networkx (==2.6.3)
Requires-Dist: numpy (==1.21.0)
Requires-Dist: pyvis (==0.1.9)
Requires-Dist: scipy (==1.7.3)
Provides-Extra: test
Requires-Dist: flake8 ; extra == 'test'
Requires-Dist: matplotlib (==3.4.2) ; extra == 'test'
Requires-Dist: myst-parser (==0.16.1) ; extra == 'test'
Requires-Dist: networkx (==2.6.3) ; extra == 'test'
Requires-Dist: numpy (==1.21.0) ; extra == 'test'
Requires-Dist: pre-commit (==2.16.0) ; extra == 'test'
Requires-Dist: pytest ; extra == 'test'
Requires-Dist: pytest-cov ; extra == 'test'
Requires-Dist: pyvis (==0.1.9) ; extra == 'test'
Requires-Dist: scipy (==1.7.3) ; extra == 'test'
Requires-Dist: sphinx (==4.3.2) ; extra == 'test'
Requires-Dist: sphinx-rtd-theme (==1.0.0) ; extra == 'test'
